mcp_server_vedb_mysql/__init__.py
mcp_server_vedb_mysql/config.py
mcp_server_vedb_mysql/server.py
vedb_mysql_mcp_server-0.1.0.dist-info/METADATA
vedb_mysql_mcp_server-0.1.0.dist-info/WHEEL
vedb_mysql_mcp_server-0.1.0.dist-info/entry_points.txt
vedb_mysql_mcp_server-0.1.0.dist-info/top_level.txt
vedb_mysql_mcp_server-0.1.0.dist-info/RECORD
