Metadata-Version: 2.4
Name: vedb-mysql-mcp-server
Version: 0.1.0
Summary: MCP server for VeDB MySQL
License: MIT
Requires-Python: >=3.13
Requires-Dist: mcp[cli]>=1.5.0
Requires-Dist: volcengine-python-sdk>=1.1.2
Requires-Dist: aiohttp>=3.11.14
Requires-Dist: deprecated>=1.2.18
